{
  "$schema": "https://static.modelcontextprotocol.io/schemas/2025-12-11/server.schema.json",
  "name": "io.github.paulhkang94/markview",
  "title": "MarkView",
  "description": "Native macOS markdown previewer (Swift, no Electron). MCP tools: open_file and preview_markdown. GFM, Mermaid, syntax highlighting, Quick Look integration.",
  "repository": {
    "url": "https://github.com/paulhkang94/markview",
    "source": "github"
  },
  "version": "1.2.6",
  "packages": [
    {
      "registryType": "npm",
      "identifier": "mcp-server-markview",
      "version": "1.2.6",
      "transport": {
        "type": "stdio"
      },
      "runtimeHint": "npx"
    }
  ]
}
